{
  "mode": "event",
  "ckpt": "hbtxr-imgsz64-epoch66-pe0.5401.ckpt",
  "grid": 16,
  "pred_centers": [
    {
      "idx": 507,
      "ts": 1657786965275272,
      "valid": false,
      "reason": "too_few_events"
    },
    {
      "idx": 508,
      "ts": 1657786965315272,
      "valid": true,
      "cx": 212.149,
      "cy": 101.562,
      "grid_x": 9.81,
      "grid_y": 6.25,
      "score": 0.7132
    },
    {
      "idx": 509,
      "ts": 1657786965355272,
      "valid": true,
      "cx": 213.725,
      "cy": 100.85,
      "grid_x": 9.883,
      "grid_y": 6.206,
      "score": 0.7231
    },
    {
      "idx": 510,
      "ts": 1657786965395272,
      "valid": true,
      "cx": 212.587,
      "cy": 101.276,
      "grid_x": 9.831,
      "grid_y": 6.232,
      "score": 0.8015
    },
    {
      "idx": 511,
      "ts": 1657786965435272,
      "valid": true,
      "cx": 213.86,
      "cy": 101.108,
      "grid_x": 9.889,
      "grid_y": 6.222,
      "score": 0.6961
    },
    {
      "idx": 512,
      "ts": 1657786965475272,
      "valid": true,
      "cx": 214.458,
      "cy": 101.442,
      "grid_x": 9.917,
      "grid_y": 6.243,
      "score": 0.622
    },
    {
      "idx": 513,
      "ts": 1657786965515272,
      "valid": true,
      "cx": 228.456,
      "cy": 103.907,
      "grid_x": 10.564,
      "grid_y": 6.394,
      "score": 0.8868
    }
  ]
}