{
  "mode": "event",
  "ckpt": "hbtxr-imgsz64-epoch66-pe0.5401.ckpt",
  "grid": 16,
  "pred_centers": [
    {
      "idx": 1707,
      "ts": 1657781042430526,
      "valid": false,
      "reason": "too_few_events"
    },
    {
      "idx": 1708,
      "ts": 1657781042470526,
      "valid": true,
      "cx": 228.307,
      "cy": 136.621,
      "grid_x": 10.558,
      "grid_y": 8.407,
      "score": 0.8583
    },
    {
      "idx": 1709,
      "ts": 1657781042510526,
      "valid": true,
      "cx": 229.537,
      "cy": 132.366,
      "grid_x": 10.614,
      "grid_y": 8.146,
      "score": 0.5436
    },
    {
      "idx": 1710,
      "ts": 1657781042550526,
      "valid": true,
      "cx": 230.708,
      "cy": 134.181,
      "grid_x": 10.669,
      "grid_y": 8.257,
      "score": 0.5679
    },
    {
      "idx": 1711,
      "ts": 1657781042590526,
      "valid": true,
      "cx": 228.713,
      "cy": 135.108,
      "grid_x": 10.576,
      "grid_y": 8.314,
      "score": 0.5808
    },
    {
      "idx": 1712,
      "ts": 1657781042630526,
      "valid": true,
      "cx": 226.656,
      "cy": 136.189,
      "grid_x": 10.481,
      "grid_y": 8.381,
      "score": 0.5959
    },
    {
      "idx": 1713,
      "ts": 1657781042670526,
      "valid": true,
      "cx": 227.011,
      "cy": 136.004,
      "grid_x": 10.498,
      "grid_y": 8.369,
      "score": 0.5779
    }
  ]
}