{
  "mode": "event",
  "ckpt": "hbtxr-imgsz64-epoch66-pe0.5401.ckpt",
  "grid": 16,
  "pred_centers": [
    {
      "idx": 105,
      "ts": 1657782729071878,
      "valid": false,
      "reason": "too_few_events"
    },
    {
      "idx": 106,
      "ts": 1657782729111878,
      "valid": true,
      "cx": 161.099,
      "cy": 104.406,
      "grid_x": 7.45,
      "grid_y": 6.425,
      "score": 0.2692
    },
    {
      "idx": 107,
      "ts": 1657782729151878,
      "valid": true,
      "cx": 185.882,
      "cy": 107.313,
      "grid_x": 8.596,
      "grid_y": 6.604,
      "score": 0.3177
    },
    {
      "idx": 108,
      "ts": 1657782729191878,
      "valid": true,
      "cx": 185.04,
      "cy": 107.009,
      "grid_x": 8.557,
      "grid_y": 6.585,
      "score": 0.3873
    },
    {
      "idx": 109,
      "ts": 1657782729231878,
      "valid": true,
      "cx": 186.526,
      "cy": 107.025,
      "grid_x": 8.625,
      "grid_y": 6.586,
      "score": 0.4549
    },
    {
      "idx": 110,
      "ts": 1657782729271878,
      "valid": true,
      "cx": 201.56,
      "cy": 106.262,
      "grid_x": 9.321,
      "grid_y": 6.539,
      "score": 0.4433
    },
    {
      "idx": 111,
      "ts": 1657782729311878,
      "valid": true,
      "cx": 201.612,
      "cy": 106.069,
      "grid_x": 9.323,
      "grid_y": 6.527,
      "score": 0.4522
    },
    {
      "idx": 112,
      "ts": 1657782729351878,
      "valid": true,
      "cx": 187.426,
      "cy": 106.302,
      "grid_x": 8.667,
      "grid_y": 6.542,
      "score": 0.4346
    },
    {
      "idx": 113,
      "ts": 1657782729391878,
      "valid": true,
      "cx": 186.471,
      "cy": 105.947,
      "grid_x": 8.623,
      "grid_y": 6.52,
      "score": 0.404
    },
    {
      "idx": 114,
      "ts": 1657782729431878,
      "valid": true,
      "cx": 202.815,
      "cy": 105.017,
      "grid_x": 9.379,
      "grid_y": 6.463,
      "score": 0.4041
    },
    {
      "idx": 115,
      "ts": 1657782729471878,
      "valid": true,
      "cx": 185.266,
      "cy": 106.144,
      "grid_x": 8.567,
      "grid_y": 6.532,
      "score": 0.4504
    }
  ]
}