{
  "mode": "event",
  "ckpt": "hbtxr-imgsz64-epoch66-pe0.5401.ckpt",
  "grid": 16,
  "pred_centers": [
    {
      "idx": 205,
      "ts": 1659072171583579,
      "valid": false,
      "reason": "too_few_events"
    },
    {
      "idx": 206,
      "ts": 1659072171623579,
      "valid": true,
      "cx": 140.718,
      "cy": 88.63,
      "grid_x": 6.507,
      "grid_y": 5.454,
      "score": 0.3457
    },
    {
      "idx": 207,
      "ts": 1659072171663579,
      "valid": true,
      "cx": 248.128,
      "cy": 105.963,
      "grid_x": 11.474,
      "grid_y": 6.521,
      "score": 0.3068
    },
    {
      "idx": 208,
      "ts": 1659072171703579,
      "valid": true,
      "cx": 248.585,
      "cy": 105.764,
      "grid_x": 11.495,
      "grid_y": 6.509,
      "score": 0.3075
    },
    {
      "idx": 209,
      "ts": 1659072171743579,
      "valid": true,
      "cx": 248.497,
      "cy": 105.885,
      "grid_x": 11.491,
      "grid_y": 6.516,
      "score": 0.2745
    },
    {
      "idx": 210,
      "ts": 1659072171783579,
      "valid": true,
      "cx": 163.686,
      "cy": 120.54,
      "grid_x": 7.569,
      "grid_y": 7.418,
      "score": 0.3592
    },
    {
      "idx": 211,
      "ts": 1659072171823579,
      "valid": true,
      "cx": 163.092,
      "cy": 119.811,
      "grid_x": 7.542,
      "grid_y": 7.373,
      "score": 0.3346
    },
    {
      "idx": 212,
      "ts": 1659072171863579,
      "valid": true,
      "cx": 247.97,
      "cy": 108.029,
      "grid_x": 11.467,
      "grid_y": 6.648,
      "score": 0.3236
    },
    {
      "idx": 213,
      "ts": 1659072171903579,
      "valid": true,
      "cx": 249.613,
      "cy": 107.56,
      "grid_x": 11.543,
      "grid_y": 6.619,
      "score": 0.3332
    },
    {
      "idx": 214,
      "ts": 1659072171943579,
      "valid": true,
      "cx": 267.051,
      "cy": 120.641,
      "grid_x": 12.349,
      "grid_y": 7.424,
      "score": 0.43
    },
    {
      "idx": 215,
      "ts": 1659072171983579,
      "valid": true,
      "cx": 264.758,
      "cy": 122.104,
      "grid_x": 12.243,
      "grid_y": 7.514,
      "score": 0.3445
    }
  ]
}