{
  "mode": "event",
  "ckpt": "hbtxr-imgsz64-epoch66-pe0.5401.ckpt",
  "grid": 16,
  "pred_centers": [
    {
      "idx": 2205,
      "ts": 1657782813113966,
      "valid": false,
      "reason": "too_few_events"
    },
    {
      "idx": 2206,
      "ts": 1657782813153966,
      "valid": true,
      "cx": 251.336,
      "cy": 142.352,
      "grid_x": 11.622,
      "grid_y": 8.76,
      "score": 0.432
    },
    {
      "idx": 2207,
      "ts": 1657782813193966,
      "valid": true,
      "cx": 250.768,
      "cy": 153.134,
      "grid_x": 11.596,
      "grid_y": 9.424,
      "score": 0.3517
    },
    {
      "idx": 2208,
      "ts": 1657782813233966,
      "valid": true,
      "cx": 225.784,
      "cy": 155.279,
      "grid_x": 10.441,
      "grid_y": 9.556,
      "score": 0.3439
    },
    {
      "idx": 2209,
      "ts": 1657782813273967,
      "valid": true,
      "cx": 188.507,
      "cy": 156.929,
      "grid_x": 8.717,
      "grid_y": 9.657,
      "score": 0.7962
    },
    {
      "idx": 2210,
      "ts": 1657782813313967,
      "valid": true,
      "cx": 189.022,
      "cy": 157.37,
      "grid_x": 8.741,
      "grid_y": 9.684,
      "score": 0.7166
    },
    {
      "idx": 2211,
      "ts": 1657782813353967,
      "valid": true,
      "cx": 189.105,
      "cy": 155.755,
      "grid_x": 8.745,
      "grid_y": 9.585,
      "score": 0.5787
    },
    {
      "idx": 2212,
      "ts": 1657782813393967,
      "valid": true,
      "cx": 200.842,
      "cy": 155.446,
      "grid_x": 9.287,
      "grid_y": 9.566,
      "score": 0.4486
    },
    {
      "idx": 2213,
      "ts": 1657782813433967,
      "valid": true,
      "cx": 202.563,
      "cy": 153.937,
      "grid_x": 9.367,
      "grid_y": 9.473,
      "score": 0.4945
    },
    {
      "idx": 2214,
      "ts": 1657782813473967,
      "valid": true,
      "cx": 184.185,
      "cy": 155.511,
      "grid_x": 8.517,
      "grid_y": 9.57,
      "score": 0.8729
    },
    {
      "idx": 2215,
      "ts": 1657782813513967,
      "valid": true,
      "cx": 183.584,
      "cy": 158.486,
      "grid_x": 8.489,
      "grid_y": 9.753,
      "score": 0.8278
    }
  ]
}