{
  "mode": "event",
  "ckpt": "hbtxr-imgsz64-epoch66-pe0.5401.ckpt",
  "grid": 16,
  "pred_centers": [
    {
      "idx": 1305,
      "ts": 1657787169957457,
      "valid": false,
      "reason": "too_few_events"
    },
    {
      "idx": 1306,
      "ts": 1657787169997457,
      "valid": true,
      "cx": 122.991,
      "cy": 78.596,
      "grid_x": 5.687,
      "grid_y": 4.837,
      "score": 0.5417
    },
    {
      "idx": 1307,
      "ts": 1657787170037457,
      "valid": true,
      "cx": 135.867,
      "cy": 84.884,
      "grid_x": 6.283,
      "grid_y": 5.224,
      "score": 0.51
    },
    {
      "idx": 1308,
      "ts": 1657787170077458,
      "valid": true,
      "cx": 138.164,
      "cy": 76.159,
      "grid_x": 6.389,
      "grid_y": 4.687,
      "score": 0.4255
    },
    {
      "idx": 1309,
      "ts": 1657787170117458,
      "valid": true,
      "cx": 123.567,
      "cy": 77.756,
      "grid_x": 5.714,
      "grid_y": 4.785,
      "score": 0.4326
    },
    {
      "idx": 1310,
      "ts": 1657787170157458,
      "valid": true,
      "cx": 120.963,
      "cy": 77.883,
      "grid_x": 5.594,
      "grid_y": 4.793,
      "score": 0.5035
    },
    {
      "idx": 1311,
      "ts": 1657787170197458,
      "valid": true,
      "cx": 118.808,
      "cy": 77.19,
      "grid_x": 5.494,
      "grid_y": 4.75,
      "score": 0.5617
    },
    {
      "idx": 1312,
      "ts": 1657787170237458,
      "valid": true,
      "cx": 119.795,
      "cy": 78.112,
      "grid_x": 5.54,
      "grid_y": 4.807,
      "score": 0.4859
    },
    {
      "idx": 1313,
      "ts": 1657787170277458,
      "valid": true,
      "cx": 113.058,
      "cy": 95.897,
      "grid_x": 5.228,
      "grid_y": 5.901,
      "score": 0.6157
    },
    {
      "idx": 1314,
      "ts": 1657787170317458,
      "valid": true,
      "cx": 101.736,
      "cy": 107.101,
      "grid_x": 4.705,
      "grid_y": 6.591,
      "score": 0.6952
    },
    {
      "idx": 1315,
      "ts": 1657787170357458,
      "valid": true,
      "cx": 110.768,
      "cy": 106.265,
      "grid_x": 5.122,
      "grid_y": 6.539,
      "score": 0.5875
    }
  ]
}