{
  "mode": "event",
  "ckpt": "hbtxr-imgsz64-epoch66-pe0.5401.ckpt",
  "grid": 16,
  "pred_centers": [
    {
      "idx": 1007,
      "ts": 1659091064770549,
      "valid": false,
      "reason": "too_few_events"
    },
    {
      "idx": 1008,
      "ts": 1659091064810549,
      "valid": true,
      "cx": 189.144,
      "cy": 127.889,
      "grid_x": 8.747,
      "grid_y": 7.87,
      "score": 0.656
    },
    {
      "idx": 1009,
      "ts": 1659091064850549,
      "valid": true,
      "cx": 189.0,
      "cy": 127.263,
      "grid_x": 8.74,
      "grid_y": 7.832,
      "score": 0.5869
    },
    {
      "idx": 1010,
      "ts": 1659091064890549,
      "valid": true,
      "cx": 188.082,
      "cy": 127.17,
      "grid_x": 8.697,
      "grid_y": 7.826,
      "score": 0.6297
    },
    {
      "idx": 1011,
      "ts": 1659091064930549,
      "valid": true,
      "cx": 187.281,
      "cy": 127.033,
      "grid_x": 8.66,
      "grid_y": 7.817,
      "score": 0.7404
    },
    {
      "idx": 1012,
      "ts": 1659091064970549,
      "valid": true,
      "cx": 184.282,
      "cy": 128.194,
      "grid_x": 8.522,
      "grid_y": 7.889,
      "score": 0.6597
    },
    {
      "idx": 1013,
      "ts": 1659091065010549,
      "valid": true,
      "cx": 172.473,
      "cy": 130.425,
      "grid_x": 7.976,
      "grid_y": 8.026,
      "score": 0.3706
    }
  ]
}